[
  {
    "time": "2026-02-13T03:50:02-0500",
    "commit": "9358f436fd4d35d955b78d5299340f702e586f04",
    "type": "improvement",
    "area": "content",
    "description": "Improve museum filters UX with icons instead of labels, compact search with icon button inside input, Landmark icon for museum filter, and museum filter moved to bottom",
    "audience": "public",
    "impact": "patch",
    "version": "2.4.1"
  },
  {
    "time": "2026-02-13T04:22:33-0500",
    "commit": "ff135a18f329a59920755317d1099a00effab8c6",
    "type": "feature",
    "area": "profile",
    "description": "Add Community following feed with Recents tab showing submissions from people you follow and load more API",
    "audience": "public",
    "impact": "minor",
    "version": "2.5.0"
  },
  {
    "time": "2026-02-13T04:22:41-0500",
    "commit": "6a960b9477e63b859eb34996482c690820cd5bf3",
    "type": "improvement",
    "area": "global",
    "description": "Add Did You Know hint for Community explaining the feed and tabs",
    "audience": "public",
    "impact": "patch",
    "version": "2.5.0"
  }
]
